anitejb/__init__.py
anitejb/safeopen.py
anitejb-1.0.0.dist-info/LICENSE
anitejb-1.0.0.dist-info/METADATA
anitejb-1.0.0.dist-info/WHEEL
anitejb-1.0.0.dist-info/top_level.txt
anitejb-1.0.0.dist-info/RECORD
