Metadata-Version: 2.1
Name: anitejb
Version: 1.0.0
Summary: A collection of custom tools and functions for @anitejb
Home-page: https://github.com/anitejb/pip
Author: Anitej Biradar
Author-email: pip@anitejb.dev
License: UNKNOWN
Project-URL: Bug Tracker, https://github.com/anitejb/pip/issues
Platform: UNKNOWN
Classifier: Programming Language :: Python :: 3.8
Classifier: License :: OSI Approved :: MIT License
Classifier: Operating System :: OS Independent
Requires-Python: >=3.8
